README.rst
setup.py
bson/__init__.py
bson/codec.py
bson/network.py
fast_bson.egg-info/PKG-INFO
fast_bson.egg-info/SOURCES.txt
fast_bson.egg-info/dependency_links.txt
fast_bson.egg-info/requires.txt
fast_bson.egg-info/top_level.txt