Metadata-Version: 1.1
Name: fast-bson
Version: 0.0.1
Summary: BSON codec for Python
Home-page: http://github.com/mmontagna/bson
Author: Marco Montagna
Author-email: marcojoemontagna@gmail.com
License: BSD
Keywords: BSON codec
Platform: Any
Classifier: Programming Language :: Python :: 2.6
Classifier: Programming Language :: Python :: 2.7
Classifier: Programming Language :: Python :: 3.3
Classifier: Programming Language :: Python :: 3.4
